blackerz_api_wrapper/__init__.py
blackerz_wrapper/__init__.py
blackerz_wrapper/__main__.py
blackerz_wrapper/lib/main.py
blackerz_wrapper/lib/warns.py
blackerz_wrapper/lib/bot/__init__.py
blackerz_wrapper/lib/bot/bot_data.py
blackerz_wrapper/lib/bot/check_vote.py
blackerz_wrapper/lib/bot/edit_bot.py
blackerz_wrapper/lib/bot/servercount.py
blackerz_wrapper/lib/util/__init__.py
blackerz_wrapper/lib/util/base_request.py
blackerz_wrapper-0.0.256.dist-info/LICENSE
blackerz_wrapper-0.0.256.dist-info/METADATA
blackerz_wrapper-0.0.256.dist-info/WHEEL
blackerz_wrapper-0.0.256.dist-info/entry_points.txt
blackerz_wrapper-0.0.256.dist-info/top_level.txt
blackerz_wrapper-0.0.256.dist-info/RECORD
