Metadata-Version: 2.1
Name: blackerz-wrapper
Version: 0.0.256
Summary: Developer kit to interact with our API
Home-page: https://github.com/Fastering18/Blackerz-Wrapper-Python
Author: Fastering18
Author-email: brahmana081@gmail.com
License: UNKNOWN
Project-URL: Bug Tracker, https://github.com/Fastering18/Blackerz-SDK-Python/issues
Platform: UNKNOWN
Classifier: Programming Language :: Python :: 3
Classifier: License :: OSI Approved :: MIT License
Classifier: Operating System :: OS Independent
Requires-Python: >=2
Requires-Dist: requests
